{"description": ["{\"data\": {\"production\":{\"id\":\"wish_i_was_here\",\"production_title\":\"Wish I Was Here\",\"production_status\":3,\"production_desc\":\"<p>Director Zach Braff's follow-up to his indie breakout hit <em>Garden State<\\/em> is a comedy telling the story of a thirtysomething man who finds himself at major crossroads, which forces him to examine his life, his career, and his family.<\\/p>\",\"in_theaters\":\"<p>July 18, 2014<\\/p>\",\"date_release\":\"2014-07-18\",\"division\":\"focus_features\",\"logo\":\"\",\"rating_img\":\"\",\"show_grid\":0,\"show_grid_filters\":0,\"show_in_theaters\":0,\"show_awards_intro\":0,\"meta_title\":\"Wish I Was Here Movie | Official Website | Buy Now | Focus Features\",\"meta_desc\":\"\",\"meta_keywords\":\"Wish I Was Here Film,buy Wish I Was Here DVD,buy Wish I Was Here Blu-Ray,Zach Braff\",\"meta_img\":\"http:\\/\\/focusmicrosites.s3.amazonaws.com\\/assets\\/img\\/og-meta.png\",\"facebook\":\"https:\\/\\/www.facebook.com\\/FocusFeatures\\/\",\"twitter\":\"https:\\/\\/twitter.com\\/FocusFeatures\",\"instagram\":\"https:\\/\\/www.instagram.com\\/focusfeatures\\/\",\"youtube_channel\":\"https:\\/\\/www.youtube.com\\/user\\/FocusFeatures\",\"tumblr_url\":\"\",\"dvd_url\":\"https:\\/\\/www.amazon.com\\/Wish-Was-Here-Zach-Braff\\/dp\\/B00MJDR97I\\/ref=tmm_dvd_swatch_0?_encoding=UTF8&qid=1484602137&sr=8-2\",\"bluray_url\":\"https:\\/\\/www.amazon.com\\/Wish-I-Was-Here\\/dp\\/B00S773DM0\\/ref=tmm_blu_swatch_0?_encoding=UTF8&qid=1484602137&sr=8-2\",\"ondemand_url\":\"https:\\/\\/www.uphe.com\\/movies\\/wish-i-was-here\",\"itunes_url\":\"https:\\/\\/www.google.com\\/url?sa=t&rct=j&q=&esrc=s&source=web&cd=1&cad=rja&uact=8&ved=0ahUKEwjZo96JzsfRAhUmh1QKHfiQD0sQFggaMAA&url=https%3A%2F%2Fitunes.apple.com%2Fus%2Fmovie%2Fwish-i-was-here%2Fid900176701&usg=AFQjCNHCIazMkodDVG7Jvu5vY-WpC0IyHw&bvm=bv.14422\",\"moviefone_id\":\"\",\"movietickets_id\":\"\",\"fandango_id\":\"\",\"related_film_title\":\"Moonrise Kingdom\",\"related_film_url\":\"http:\\/\\/focusfeatures.com\\/moonrise_kingdom\",\"related_film_thumb\":\"http:\\/\\/focusmicrosites.s3.amazonaws.com\\/assets\\/uploads\\/thumb_587c2020f1ddd.jpg\",\"code_head\":\"\",\"code_body_top\":\"\",\"code_body_bottom\":\"\",\"theme_colors\":\"white\",\"theme_fonts\":\"sans-serif\",\"theme_hl\":\"227,32,201\",\"theme_bg\":\"\",\"intro_video_id\":0,\"categories\":[],\"gallery\":[{\"id\":\"video_official_trailer_1\",\"aid\":699,\"content_type\":\"video\",\"title\":\"<p>Official Trailer: <em>Wish I Was Here<\\/em><\\/p>\",\"short_desc\":\"<p>Focus Features proudly presents Zach Braff&rsquo;s second directorial feature.&nbsp;<\\/p>\",\"description\":\"\",\"is_featured\":0,\"is_trailer\":0,\"external_url\":\"https:\\/\\/www.youtube.com\\/watch?v=iKfqbfLa9qY\",\"columns\":2,\"max_width\":0,\"thumb\":\"http:\\/\\/focusmicrosites.s3.amazonaws.com\\/assets\\/uploads\\/_tmp\\/1484722034_focusfeatures_wishiwashere_zachbraff_piercegagnon_joeyking_katehudson_jimparsons_mandypatinkin_joshgad_trailer1-796x448.jpg\",\"related_items\":[],\"tags\":\"\",\"loop_vid\":0,\"img\":\"http:\\/\\/focusmicrosites.s3.amazonaws.com\\/assets\\/uploads\\/1484722034_focusfeatures_wishiwashere_zachbraff_piercegagnon_joeyking_katehudson_jimparsons_mandypatinkin_joshgad_trailer1.jpg\",\"video\":\"https:\\/\\/www.youtube.com\\/watch?v=iKfqbfLa9qY\"}],\"backgrounds\":[{\"id\":\"700\",\"aid\":700,\"content_type\":\"image\",\"loop_vid\":0,\"img\":\"http:\\/\\/focusmicrosites.s3.amazonaws.com\\/assets\\/uploads\\/1484602332_focusfeatures_wishiwashere_zachbraff_piercegagnon_joeyking_katehudson_jimparsons_mandypatinkin_joshgad_bg1.jpg\",\"video\":\"\"},{\"id\":\"701\",\"aid\":701,\"content_type\":\"image\",\"loop_vid\":0,\"img\":\"http:\\/\\/focusmicrosites.s3.amazonaws.com\\/assets\\/uploads\\/1484602341_focusfeatures_wishiwashere_zachbraff_piercegagnon_joeyking_katehudson_jimparsons_mandypatinkin_joshgad_bg2.jpg\",\"video\":\"\"},{\"id\":\"702\",\"aid\":702,\"content_type\":\"image\",\"loop_vid\":0,\"img\":\"http:\\/\\/focusmicrosites.s3.amazonaws.com\\/assets\\/uploads\\/1484602351_focusfeatures_wishiwashere_zachbraff_piercegagnon_joeyking_katehudson_jimparsons_mandypatinkin_joshgad_bg3.jpg\",\"video\":\"\"},{\"id\":\"703\",\"aid\":703,\"content_type\":\"image\",\"loop_vid\":0,\"img\":\"http:\\/\\/focusmicrosites.s3.amazonaws.com\\/assets\\/uploads\\/1484602359_focusfeatures_wishiwashere_zachbraff_piercegagnon_joeyking_katehudson_jimparsons_mandypatinkin_joshgad_bg4.jpg\",\"video\":\"\"},{\"id\":\"704\",\"aid\":704,\"content_type\":\"image\",\"loop_vid\":0,\"img\":\"http:\\/\\/focusmicrosites.s3.amazonaws.com\\/assets\\/uploads\\/1484602368_focusfeatures_wishiwashere_zachbraff_piercegagnon_joeyking_katehudson_jimparsons_mandypatinkin_joshgad_bg5.jpg\",\"video\":\"\"}],\"modules\":[{\"module_id\":\"3\",\"title\":\"OWN IT\",\"alignment\":\"left\"},{\"module_id\":\"7\",\"title\":\"SOCIAL\",\"alignment\":\"right\"}],\"news\":[],\"partners\":[],\"reactions\":[],\"trending\":[],\"castcrew\":[{\"id\":\"4718\",\"full_name\":\"Zach Braff\",\"person_role\":\"Aidan\",\"url\":\"\",\"is_cast\":\"1\"},{\"id\":\"4373\",\"full_name\":\"Kate Hudson\",\"person_role\":\"Sarah\",\"url\":\"\",\"is_cast\":\"1\"},{\"id\":\"4375\",\"full_name\":\"Mandy Patinkin\",\"person_role\":\"Gabe\",\"url\":\"\",\"is_cast\":\"1\"},{\"id\":\"4377\",\"full_name\":\"Josh Gad\",\"person_role\":\"Noah\",\"url\":\"\",\"is_cast\":\"1\"},{\"id\":\"4379\",\"full_name\":\"Joey King\",\"person_role\":\"Grace\",\"url\":\"\",\"is_cast\":\"1\"},{\"id\":\"4381\",\"full_name\":\"Pierce Gagnon\",\"person_role\":\"Tucker\",\"url\":\"\",\"is_cast\":\"1\"},{\"id\":\"4383\",\"full_name\":\"Donald Faison\",\"person_role\":\"Anthony\",\"url\":\"\",\"is_cast\":\"1\"},{\"id\":\"4385\",\"full_name\":\"Ashley Green\",\"person_role\":\"Janine\",\"url\":\"\",\"is_cast\":\"1\"},{\"id\":\"4387\",\"full_name\":\"Jim Parsons\",\"person_role\":\"Paul\",\"url\":\"\",\"is_cast\":\"1\"},{\"id\":\"4389\",\"full_name\":\"Michael Weston\",\"person_role\":\"Jerry\",\"url\":\"\",\"is_cast\":\"1\"},{\"id\":\"4372\",\"full_name\":\"Zach Braff\",\"person_role\":\"Writer, Director\",\"url\":\"\",\"is_cast\":\"0\"},{\"id\":\"4374\",\"full_name\":\"Adam Braff\",\"person_role\":\"Writer, Producer\",\"url\":\"\",\"is_cast\":\"0\"},{\"id\":\"4376\",\"full_name\":\"Stacey Sher\",\"person_role\":\"Producer\",\"url\":\"\",\"is_cast\":\"0\"},{\"id\":\"4378\",\"full_name\":\"Michael Shamberg\",\"person_role\":\"Producer\",\"url\":\"\",\"is_cast\":\"0\"},{\"id\":\"4380\",\"full_name\":\"Lawrence Sher\",\"person_role\":\"Director of Photography\",\"url\":\"\",\"is_cast\":\"0\"},{\"id\":\"4382\",\"full_name\":\"Tony Fanning\",\"person_role\":\"Production Designer\",\"url\":\"\",\"is_cast\":\"0\"},{\"id\":\"4384\",\"full_name\":\"Myron Kerstein\",\"person_role\":\"Editor\",\"url\":\"\",\"is_cast\":\"0\"},{\"id\":\"4386\",\"full_name\":\"Betsy Heimann\",\"person_role\":\"Costume Designer\",\"url\":\"\",\"is_cast\":\"0\"},{\"id\":\"4388\",\"full_name\":\"Rob Simonsen\",\"person_role\":\"Music\",\"url\":\"\",\"is_cast\":\"0\"}],\"awards\":[]},\"spriteVersion\":\"13\",\"cssVersion\":\"118.13\",\"jsVersion\":\"117.13\",\"jsonPath\":\"http:\\/\\/focusmicrosites.s3.amazonaws.com\\/assets\\/uploads\\/_tmp\\/productionswish_i_was_here\",\"status\":\"ok\",\"usedDB\":0}}"], "url": "focusfeatures.com/wish_i_was_here", "_type": "x"}