{"description": ["{\"data\": {\"production\":{\"id\":\"eternal_sunshine_of_the_spotless_mind\",\"production_title\":\"Eternal Sunshine of the Spotless Mind\",\"production_status\":3,\"production_desc\":\"<p><a href=\\\"http:\\/\\/www.imdb.com\\/name\\/nm0000120?ref_=tt_ov_st_sm\\\" target=\\\"_blank\\\"><span style=\\\"text-decoration: underline;\\\"><strong>Jim Carrey<\\/strong><\\/span><\\/a> heads the cast of <strong><em>Eternal Sunshine of the Spotless Mind<\\/em><\\/strong>, directed by <a href=\\\"http:\\/\\/www.imdb.com\\/name\\/nm0327273?ref_=tt_ov_dr\\\" target=\\\"_blank\\\"><span style=\\\"text-decoration: underline;\\\"><strong>Michel Gondry<\\/strong><\\/span><\\/a> from Academy Award nominee <a href=\\\"http:\\/\\/www.imdb.com\\/name\\/nm0442109?ref_=tt_ov_wr\\\" target=\\\"_blank\\\"><span style=\\\"text-decoration: underline;\\\"><strong>Charlie Kaufman's<\\/strong><\\/span><\\/a> (<a href=\\\"http:\\/\\/www.imdb.com\\/title\\/tt0268126\\/?ref_=nm_flmg_wr_8\\\" target=\\\"_blank\\\"><span style=\\\"text-decoration: underline;\\\"><strong><em>Adaptation.<\\/em><\\/strong><\\/span><\\/a>) original screenplay. The two-time Golden Globe Award winner is joined in the movie by three-time Academy Award nominee <a href=\\\"http:\\/\\/www.imdb.com\\/name\\/nm0000701?ref_=tt_ov_st_sm\\\" target=\\\"_blank\\\"><span style=\\\"text-decoration: underline;\\\"><strong>Kate Winslet<\\/strong><\\/span><\\/a>, <a href=\\\"http:\\/\\/www.imdb.com\\/name\\/nm0000379\\/?ref_=tt_cl_t9\\\" target=\\\"_blank\\\"><span style=\\\"text-decoration: underline;\\\"><strong>Kirsten Dunst<\\/strong><\\/span><\\/a>,&nbsp;<a href=\\\"http:\\/\\/www.imdb.com\\/name\\/nm0929489\\/?ref_=tt_cl_t10\\\" target=\\\"_blank\\\"><span style=\\\"text-decoration: underline;\\\"><strong>Tom Wilkinson<\\/strong><\\/span><\\/a>, <a href=\\\"http:\\/\\/www.imdb.com\\/name\\/nm0749263\\/?ref_=tt_cl_t6\\\" target=\\\"_blank\\\"><span style=\\\"text-decoration: underline;\\\"><strong>Mark Ruffalo<\\/strong><\\/span><\\/a>, and <a href=\\\"http:\\/\\/www.imdb.com\\/name\\/nm0000704\\/?ref_=tt_cl_t4\\\" target=\\\"_blank\\\"><span style=\\\"text-decoration: underline;\\\"><strong>Elijah Wood<\\/strong><\\/span><\\/a>.<!-- pagebreak --><\\/p><p>Joel (Jim Carrey) is stunned to discover that his girlfriend Clementine (Kate Winslet) has had her memories of their tumultuous relationship erased. Out of desperation, he contacts the inventor of the process, Dr. Howard Mierzwiak (Tom Wilkinson), to have Clementine removed from his own memory. But as Joel's memories progressively disappear, he begins to rediscover his love for Clementine. From deep within the recesses of his brain, Joel attempts to escape the procedure. As Dr. Mierzwiak and his crew (Kirsten Dunst, Mark Ruffalo, Elijah Wood) chase him through the maze of his memories, it's clear that Joel just can't get Clementine out of his head.<\\/p>\",\"in_theaters\":\"<p>March 19, 2004<\\/p>\",\"date_release\":\"2004-03-19\",\"division\":\"focus_features\",\"logo\":\"\",\"rating_img\":\"\",\"show_grid\":1,\"show_grid_filters\":1,\"show_in_theaters\":0,\"show_awards_intro\":0,\"meta_title\":\"Eternal Sunshine of the Spotless Mind Movie | Official Website | Buy Now | Focus Features\",\"meta_desc\":\"After finding out that his girlfriend Clementine (Kate Winslet) has had him erased from her memory, Joel (Jim Carrey) seeks out the inventor of the process to do the same. Directed by visionary director Michel Gondry and written by Academy Award nominee Charlie Kaufman.\",\"meta_keywords\":\"Eternal Sunshine of the Spotless Mind Film,buy Eternal Sunshine of the Spotless Mind DVD,buy Eternal Sunshine of the Spotless Mind Blu-Ray,Michel Gondry\",\"meta_img\":\"http:\\/\\/focusmicrosites.s3.amazonaws.com\\/assets\\/img\\/og-meta.png\",\"facebook\":\"https:\\/\\/www.facebook.com\\/FocusFeatures\\/\",\"twitter\":\"https:\\/\\/twitter.com\\/FocusFeatures\",\"instagram\":\"https:\\/\\/www.instagram.com\\/focusfeatures\\/\",\"youtube_channel\":\"https:\\/\\/www.youtube.com\\/user\\/FocusFeatures\",\"tumblr_url\":\"\",\"dvd_url\":\"https:\\/\\/www.amazon.com\\/Eternal-Sunshine-Spotless-Mind-Carrey\\/dp\\/B00005JMJG\\/ref=sr_1_3_twi_dvd_1?s=movies-tv&ie=UTF8&qid=1484704848&sr=1-3&keywords=Eternal+Sunshine+of+the+Spotless+Mind+Movie\",\"bluray_url\":\"https:\\/\\/www.amazon.com\\/Eternal-Sunshine-Spotless-Mind-BLU-RAY\\/dp\\/B005HI4LOQ\\/ref=tmm_blu_swatch_0?_encoding=UTF8&qid=1484704848&sr=1-3\",\"ondemand_url\":\"https:\\/\\/www.uphe.com\\/movies\\/eternal-sunshine-of-the-spotless-mind\",\"itunes_url\":\"https:\\/\\/itunes.apple.com\\/us\\/movie\\/eternal-sunshine-spotless\\/id303440550\",\"moviefone_id\":\"\",\"movietickets_id\":\"\",\"fandango_id\":\"\",\"related_film_title\":null,\"related_film_url\":\"http:\\/\\/focusfeatures.com\\/\",\"related_film_thumb\":\"\",\"code_head\":\"\",\"code_body_top\":\"\",\"code_body_bottom\":\"\",\"theme_colors\":\"white\",\"theme_fonts\":\"sans-serif\",\"theme_hl\":\"227,104,22\",\"theme_bg\":\"22,27,31\",\"intro_video_id\":0,\"categories\":[{\"id\":\"125\",\"parent_id\":\"0\",\"categories\":[{\"id\":\"126\",\"parent_id\":\"125\",\"categories\":[],\"title\":\"Unit\",\"active\":1},{\"id\":\"127\",\"parent_id\":\"125\",\"categories\":[],\"title\":\"Behind the Scenes\",\"active\":1}],\"title\":\"Photos\",\"active\":1},{\"id\":\"128\",\"parent_id\":\"0\",\"categories\":[{\"id\":\"129\",\"parent_id\":\"128\",\"categories\":[],\"title\":\"Jim Carrey\",\"active\":1},{\"id\":\"130\",\"parent_id\":\"128\",\"categories\":[],\"title\":\"Kate Winslet\",\"active\":1},{\"id\":\"131\",\"parent_id\":\"128\",\"categories\":[],\"title\":\"Elijah Wood\",\"active\":1},{\"id\":\"132\",\"parent_id\":\"128\",\"categories\":[],\"title\":\"Mark Ruffalo\",\"active\":1},{\"id\":\"133\",\"parent_id\":\"128\",\"categories\":[],\"title\":\"Kirsten Dunst\",\"active\":1},{\"id\":\"134\",\"parent_id\":\"128\",\"categories\":[],\"title\":\"Tom Wilkinson\",\"active\":1},{\"id\":\"135\",\"parent_id\":\"128\",\"categories\":[],\"title\":\"Michel Gondry\",\"active\":1},{\"id\":\"136\",\"parent_id\":\"128\",\"categories\":[],\"title\":\"Charlie Kaufman\",\"active\":1}],\"title\":\"Cast + Filmmakers\",\"active\":1},{\"id\":\"123\",\"parent_id\":\"0\",\"categories\":[{\"id\":\"124\",\"parent_id\":\"123\",\"categories\":[],\"title\":\"Reaction\",\"active\":1}],\"title\":\"Video\",\"active\":1},{\"id\":\"121\",\"parent_id\":\"0\",\"categories\":[{\"id\":\"122\",\"parent_id\":\"121\",\"categories\":[],\"title\":\"Quotes\",\"active\":1}],\"title\":\"News + Reactions\",\"active\":1}],\"gallery\":[{\"id\":\"photos_unit_3\",\"aid\":601,\"content_type\":\"image\",\"title\":\"\",\"short_desc\":\"\",\"description\":\"\",\"is_featured\":0,\"is_trailer\":0,\"external_url\":\"\",\"columns\":3,\"max_width\":1201,\"thumb\":\"http:\\/\\/focusmicrosites.s3.amazonaws.com\\/assets\\/uploads\\/_tmp\\/1483669966_focus_features_eternal_sunshine_of_the_spotless_mind_jim_carrey_kate_winslet_kirsten_dunst_mark_ruffalo_elijah_wood_michel_gondry_charlie_kaufman_gallery4-1194x647.jpg\",\"related_items\":[],\"tags\":\" c125 c126 c129 c\",\"loop_vid\":0,\"img\":\"http:\\/\\/focusmicrosites.s3.amazonaws.com\\/assets\\/uploads\\/1483669966_focus_features_eternal_sunshine_of_the_spotless_mind_jim_carrey_kate_winslet_kirsten_dunst_mark_ruffalo_elijah_wood_michel_gondry_charlie_kaufman_gallery4.jpg\",\"video\":\"\"},{\"id\":\"photos_unit_4\",\"aid\":602,\"content_type\":\"image\",\"title\":\"\",\"short_desc\":\"\",\"description\":\"\",\"is_featured\":0,\"is_trailer\":0,\"external_url\":\"\",\"columns\":1,\"max_width\":1201,\"thumb\":\"http:\\/\\/focusmicrosites.s3.amazonaws.com\\/assets\\/uploads\\/_tmp\\/1483669996_focus_features_eternal_sunshine_of_the_spotless_mind_jim_carrey_kate_winslet_kirsten_dunst_mark_ruffalo_elijah_wood_michel_gondry_charlie_kaufman_gallery5-398x596.jpg\",\"related_items\":[],\"tags\":\" c125 c126 c133 c\",\"loop_vid\":0,\"img\":\"http:\\/\\/focusmicrosites.s3.amazonaws.com\\/assets\\/uploads\\/1483669996_focus_features_eternal_sunshine_of_the_spotless_mind_jim_carrey_kate_winslet_kirsten_dunst_mark_ruffalo_elijah_wood_michel_gondry_charlie_kaufman_gallery5.jpg\",\"video\":\"\"},{\"id\":\"photos_unit_5\",\"aid\":603,\"content_type\":\"image\",\"title\":\"\",\"short_desc\":\"\",\"description\":\"\",\"is_featured\":0,\"is_trailer\":0,\"external_url\":\"\",\"columns\":1,\"max_width\":1201,\"thumb\":\"http:\\/\\/focusmicrosites.s3.amazonaws.com\\/assets\\/uploads\\/_tmp\\/1483670024_focus_features_eternal_sunshine_of_the_spotless_mind_jim_carrey_kate_winslet_kirsten_dunst_mark_ruffalo_elijah_wood_michel_gondry_charlie_kaufman_gallery6-398x224.jpg\",\"related_items\":[],\"tags\":\" c125 c126 c129 c134 c\",\"loop_vid\":0,\"img\":\"http:\\/\\/focusmicrosites.s3.amazonaws.com\\/assets\\/uploads\\/1483670024_focus_features_eternal_sunshine_of_the_spotless_mind_jim_carrey_kate_winslet_kirsten_dunst_mark_ruffalo_elijah_wood_michel_gondry_charlie_kaufman_gallery6.jpg\",\"video\":\"\"},{\"id\":\"620\",\"aid\":620,\"content_type\":\"newsletter\",\"title\":\"<p>Sign Up For Focus Firsts<\\/p>\",\"short_desc\":\"\",\"description\":\"\",\"is_featured\":0,\"is_trailer\":0,\"external_url\":\"\",\"columns\":1,\"max_width\":0,\"thumb\":\"\",\"related_items\":[],\"tags\":\"\",\"loop_vid\":0,\"img\":\"\",\"video\":\"\"},{\"id\":\"photos_unit_6\",\"aid\":604,\"content_type\":\"image\",\"title\":\"\",\"short_desc\":\"\",\"description\":\"\",\"is_featured\":0,\"is_trailer\":0,\"external_url\":\"\",\"columns\":1,\"max_width\":1201,\"thumb\":\"http:\\/\\/focusmicrosites.s3.amazonaws.com\\/assets\\/uploads\\/_tmp\\/1483670059_focus_features_eternal_sunshine_of_the_spotless_mind_jim_carrey_kate_winslet_kirsten_dunst_mark_ruffalo_elijah_wood_michel_gondry_charlie_kaufman_gallery7-398x224.jpg\",\"related_items\":[],\"tags\":\" c125 c126 c132 c133 c134 c\",\"loop_vid\":0,\"img\":\"http:\\/\\/focusmicrosites.s3.amazonaws.com\\/assets\\/uploads\\/1483670059_focus_features_eternal_sunshine_of_the_spotless_mind_jim_carrey_kate_winslet_kirsten_dunst_mark_ruffalo_elijah_wood_michel_gondry_charlie_kaufman_gallery7.jpg\",\"video\":\"\"},{\"id\":\"photos_unit_7\",\"aid\":605,\"content_type\":\"image\",\"title\":\"\",\"short_desc\":\"\",\"description\":\"\",\"is_featured\":0,\"is_trailer\":0,\"external_url\":\"\",\"columns\":1,\"max_width\":1201,\"thumb\":\"http:\\/\\/focusmicrosites.s3.amazonaws.com\\/assets\\/uploads\\/_tmp\\/1483670085_focus_features_eternal_sunshine_of_the_spotless_mind_jim_carrey_kate_winslet_kirsten_dunst_mark_ruffalo_elijah_wood_michel_gondry_charlie_kaufman_gallery8-398x214.jpg\",\"related_items\":[],\"tags\":\" c125 c126 c129 c130 c\",\"loop_vid\":0,\"img\":\"http:\\/\\/focusmicrosites.s3.amazonaws.com\\/assets\\/uploads\\/1483670085_focus_features_eternal_sunshine_of_the_spotless_mind_jim_carrey_kate_winslet_kirsten_dunst_mark_ruffalo_elijah_wood_michel_gondry_charlie_kaufman_gallery8.jpg\",\"video\":\"\"},{\"id\":\"592\",\"aid\":592,\"content_type\":\"quote\",\"title\":\"<p>Entertainment Weekly - Owen Gleiberman - \\\"You fall in love...\\\"<\\/p>\",\"short_desc\":\"\",\"description\":\"<p>Watching <em>Eternal Sunshine<\\/em>, you don't just watch a love story -- you fall in love with what love really is.<\\/p>\",\"is_featured\":0,\"is_trailer\":0,\"external_url\":\"http:\\/\\/ew.com\\/article\\/2007\\/07\\/26\\/eternal-sunshine-spotless-mind-5\\/\",\"columns\":1,\"max_width\":0,\"thumb\":\"\",\"related_items\":[],\"tags\":\" c121 c122 c\",\"quote_author\":\"OWEN GLEIBERMAN\",\"quote_source\":\"ENTERTAINMENT WEEKLY\",\"rating\":\"\",\"rating_max\":4,\"loop_vid\":0,\"img\":\"\",\"video\":\"\"},{\"id\":\"photos_unit_8\",\"aid\":606,\"content_type\":\"image\",\"title\":\"\",\"short_desc\":\"\",\"description\":\"\",\"is_featured\":0,\"is_trailer\":0,\"external_url\":\"\",\"columns\":2,\"max_width\":1201,\"thumb\":\"http:\\/\\/focusmicrosites.s3.amazonaws.com\\/assets\\/uploads\\/_tmp\\/1483670114_focus_features_eternal_sunshine_of_the_spotless_mind_jim_carrey_kate_winslet_kirsten_dunst_mark_ruffalo_elijah_wood_michel_gondry_charlie_kaufman_gallery9-796x429.jpg\",\"related_items\":[],\"tags\":\" c125 c126 c129 c\",\"loop_vid\":0,\"img\":\"http:\\/\\/focusmicrosites.s3.amazonaws.com\\/assets\\/uploads\\/1483670114_focus_features_eternal_sunshine_of_the_spotless_mind_jim_carrey_kate_winslet_kirsten_dunst_mark_ruffalo_elijah_wood_michel_gondry_charlie_kaufman_gallery9.jpg\",\"video\":\"\"},{\"id\":\"photos_unit_9\",\"aid\":607,\"content_type\":\"image\",\"title\":\"\",\"short_desc\":\"\",\"description\":\"\",\"is_featured\":0,\"is_trailer\":0,\"external_url\":\"\",\"columns\":1,\"max_width\":1201,\"thumb\":\"http:\\/\\/focusmicrosites.s3.amazonaws.com\\/assets\\/uploads\\/_tmp\\/1483670152_focus_features_eternal_sunshine_of_the_spotless_mind_jim_carrey_kate_winslet_kirsten_dunst_mark_ruffalo_elijah_wood_michel_gondry_charlie_kaufman_gallery13-398x224.jpg\",\"related_items\":[],\"tags\":\" c125 c126 c133 c134 c\",\"loop_vid\":0,\"img\":\"http:\\/\\/focusmicrosites.s3.amazonaws.com\\/assets\\/uploads\\/1483670152_focus_features_eternal_sunshine_of_the_spotless_mind_jim_carrey_kate_winslet_kirsten_dunst_mark_ruffalo_elijah_wood_michel_gondry_charlie_kaufman_gallery13.jpg\",\"video\":\"\"},{\"id\":\"593\",\"aid\":593,\"content_type\":\"quote\",\"title\":\"<p>WSJ - Joe Morganstern - \\\"...film lovers crave\\\"<\\/p>\",\"short_desc\":\"\",\"description\":\"<p>One of those rare collaborations that artists dream of, and that film lovers crave.<\\/p>\",\"is_featured\":0,\"is_trailer\":0,\"external_url\":\"http:\\/\\/www.wsj.com\\/articles\\/SB107965692804159910\",\"columns\":1,\"max_width\":0,\"thumb\":\"\",\"related_items\":[],\"tags\":\" c121 c122 c\",\"quote_author\":\"JOE MORGANSTERN\",\"quote_source\":\"THE WALL STREET JOURNAL\",\"rating\":\"\",\"rating_max\":4,\"loop_vid\":0,\"img\":\"\",\"video\":\"\"},{\"id\":\"photos_unit_9\",\"aid\":608,\"content_type\":\"image\",\"title\":\"\",\"short_desc\":\"\",\"description\":\"\",\"is_featured\":0,\"is_trailer\":0,\"external_url\":\"\",\"columns\":2,\"max_width\":1201,\"thumb\":\"http:\\/\\/focusmicrosites.s3.amazonaws.com\\/assets\\/uploads\\/_tmp\\/1483670179_focus_features_eternal_sunshine_of_the_spotless_mind_jim_carrey_kate_winslet_kirsten_dunst_mark_ruffalo_elijah_wood_michel_gondry_charlie_kaufman_gallery15-796x425.jpg\",\"related_items\":[],\"tags\":\" c125 c126 c132 c\",\"loop_vid\":0,\"img\":\"http:\\/\\/focusmicrosites.s3.amazonaws.com\\/assets\\/uploads\\/1483670179_focus_features_eternal_sunshine_of_the_spotless_mind_jim_carrey_kate_winslet_kirsten_dunst_mark_ruffalo_elijah_wood_michel_gondry_charlie_kaufman_gallery15.jpg\",\"video\":\"\"},{\"id\":\"photos_unit_10\",\"aid\":609,\"content_type\":\"image\",\"title\":\"\",\"short_desc\":\"\",\"description\":\"\",\"is_featured\":0,\"is_trailer\":0,\"external_url\":\"\",\"columns\":1,\"max_width\":1201,\"thumb\":\"http:\\/\\/focusmicrosites.s3.amazonaws.com\\/assets\\/uploads\\/_tmp\\/1483670203_focus_features_eternal_sunshine_of_the_spotless_mind_jim_carrey_kate_winslet_kirsten_dunst_mark_ruffalo_elijah_wood_michel_gondry_charlie_kaufman_gallery16-398x224.jpg\",\"related_items\":[],\"tags\":\" c125 c126 c129 c\",\"loop_vid\":0,\"img\":\"http:\\/\\/focusmicrosites.s3.amazonaws.com\\/assets\\/uploads\\/1483670203_focus_features_eternal_sunshine_of_the_spotless_mind_jim_carrey_kate_winslet_kirsten_dunst_mark_ruffalo_elijah_wood_michel_gondry_charlie_kaufman_gallery16.jpg\",\"video\":\"\"},{\"id\":\"photos_unit_11\",\"aid\":610,\"content_type\":\"image\",\"title\":\"\",\"short_desc\":\"\",\"description\":\"\",\"is_featured\":0,\"is_trailer\":0,\"external_url\":\"\",\"columns\":3,\"max_width\":1201,\"thumb\":\"http:\\/\\/focusmicrosites.s3.amazonaws.com\\/assets\\/uploads\\/_tmp\\/1483670230_focus_features_eternal_sunshine_of_the_spotless_mind_jim_carrey_kate_winslet_kirsten_dunst_mark_ruffalo_elijah_wood_michel_gondry_charlie_kaufman_gallery17-1194x642.jpg\",\"related_items\":[],\"tags\":\" c125 c126 c129 c130 c\",\"loop_vid\":0,\"img\":\"http:\\/\\/focusmicrosites.s3.amazonaws.com\\/assets\\/uploads\\/1483670230_focus_features_eternal_sunshine_of_the_spotless_mind_jim_carrey_kate_winslet_kirsten_dunst_mark_ruffalo_elijah_wood_michel_gondry_charlie_kaufman_gallery17.jpg\",\"video\":\"\"},{\"id\":\"596\",\"aid\":596,\"content_type\":\"quote\",\"title\":\"<p>Time - Richard Corliss - \\\"...intellectually provocative...\\\"<\\/p>\",\"short_desc\":\"\",\"description\":\"<p><em>Eternal Sunshine of the Spotless Mind<\\/em>, the latest and loveliest alternative universe created by Charlie Kaufman, America's most &mdash; we should probably say only &mdash; intellectually provocative screenwriter.<\\/p>\",\"is_featured\":0,\"is_trailer\":0,\"external_url\":\"http:\\/\\/content.time.com\\/time\\/magazine\\/article\\/0,9171,1101040322-600893,00.html\",\"columns\":1,\"max_width\":0,\"thumb\":\"\",\"related_items\":[],\"tags\":\" c121 c122 c\",\"quote_author\":\"RICHARD CORLISS\",\"quote_source\":\"TIME\",\"rating\":\"\",\"rating_max\":4,\"loop_vid\":0,\"img\":\"\",\"video\":\"\"},{\"id\":\"photos_unit_13\",\"aid\":612,\"content_type\":\"image\",\"title\":\"\",\"short_desc\":\"\",\"description\":\"\",\"is_featured\":0,\"is_trailer\":0,\"external_url\":\"\",\"columns\":2,\"max_width\":1201,\"thumb\":\"http:\\/\\/focusmicrosites.s3.amazonaws.com\\/assets\\/uploads\\/_tmp\\/1483670277_focus_features_eternal_sunshine_of_the_spotless_mind_jim_carrey_kate_winslet_kirsten_dunst_mark_ruffalo_elijah_wood_michel_gondry_charlie_kaufman_gallery19-796x448.jpg\",\"related_items\":[],\"tags\":\" c125 c126 c129 c\",\"loop_vid\":0,\"img\":\"http:\\/\\/focusmicrosites.s3.amazonaws.com\\/assets\\/uploads\\/1483670277_focus_features_eternal_sunshine_of_the_spotless_mind_jim_carrey_kate_winslet_kirsten_dunst_mark_ruffalo_elijah_wood_michel_gondry_charlie_kaufman_gallery19.jpg\",\"video\":\"\"},{\"id\":\"photos_unit_14\",\"aid\":613,\"content_type\":\"image\",\"title\":\"\",\"short_desc\":\"\",\"description\":\"\",\"is_featured\":0,\"is_trailer\":0,\"external_url\":\"\",\"columns\":3,\"max_width\":1201,\"thumb\":\"http:\\/\\/focusmicrosites.s3.amazonaws.com\\/assets\\/uploads\\/_tmp\\/1483670303_focus_features_eternal_sunshine_of_the_spotless_mind_jim_carrey_kate_winslet_kirsten_dunst_mark_ruffalo_elijah_wood_michel_gondry_charlie_kaufman_gallery20-1194x639.jpg\",\"related_items\":[],\"tags\":\" c125 c126 c129 c\",\"loop_vid\":0,\"img\":\"http:\\/\\/focusmicrosites.s3.amazonaws.com\\/assets\\/uploads\\/1483670303_focus_features_eternal_sunshine_of_the_spotless_mind_jim_carrey_kate_winslet_kirsten_dunst_mark_ruffalo_elijah_wood_michel_gondry_charlie_kaufman_gallery20.jpg\",\"video\":\"\"},{\"id\":\"595\",\"aid\":595,\"content_type\":\"quote\",\"title\":\"<p>Rolling Stone - Peter Travers - \\\"...ballsy movie...\\\"<\\/p>\",\"short_desc\":\"\",\"description\":\"<p>Chases so many ideas that it threatens to spin out of control. But with our multiplexes stuffed with toxic Hollywood formula, it's a gift to find a ballsy movie that thinks it can do anything, and damn near does.<\\/p>\",\"is_featured\":0,\"is_trailer\":0,\"external_url\":\"http:\\/\\/www.rollingstone.com\\/movies\\/reviews\\/eternal-sunshine-of-the-spotless-mind-20040310\",\"columns\":1,\"max_width\":0,\"thumb\":\"\",\"related_items\":[],\"tags\":\" c121 c122 c\",\"quote_author\":\"PETER TRAVERS\",\"quote_source\":\"ROLLING STONE\",\"rating\":\"\",\"rating_max\":4,\"loop_vid\":0,\"img\":\"\",\"video\":\"\"},{\"id\":\"photos_bts_1\",\"aid\":614,\"content_type\":\"image\",\"title\":\"\",\"short_desc\":\"\",\"description\":\"\",\"is_featured\":0,\"is_trailer\":0,\"external_url\":\"\",\"columns\":2,\"max_width\":1201,\"thumb\":\"http:\\/\\/focusmicrosites.s3.amazonaws.com\\/assets\\/uploads\\/_tmp\\/1483670333_focus_features_eternal_sunshine_of_the_spotless_mind_jim_carrey_kate_winslet_kirsten_dunst_mark_ruffalo_elijah_wood_michel_gondry_charlie_kaufman_gallery2-796x533.jpg\",\"related_items\":[],\"tags\":\" c125 c127 c129 c135 c\",\"loop_vid\":0,\"img\":\"http:\\/\\/focusmicrosites.s3.amazonaws.com\\/assets\\/uploads\\/1483670333_focus_features_eternal_sunshine_of_the_spotless_mind_jim_carrey_kate_winslet_kirsten_dunst_mark_ruffalo_elijah_wood_michel_gondry_charlie_kaufman_gallery2.jpg\",\"video\":\"\"},{\"id\":\"photos_bts_2\",\"aid\":615,\"content_type\":\"image\",\"title\":\"\",\"short_desc\":\"\",\"description\":\"\",\"is_featured\":0,\"is_trailer\":0,\"external_url\":\"\",\"columns\":2,\"max_width\":1201,\"thumb\":\"http:\\/\\/focusmicrosites.s3.amazonaws.com\\/assets\\/uploads\\/_tmp\\/1483670370_focus_features_eternal_sunshine_of_the_spotless_mind_jim_carrey_kate_winslet_kirsten_dunst_mark_ruffalo_elijah_wood_michel_gondry_charlie_kaufman_gallery10-796x508.jpg\",\"related_items\":[],\"tags\":\" c125 c127 c129 c130 c\",\"loop_vid\":0,\"img\":\"http:\\/\\/focusmicrosites.s3.amazonaws.com\\/assets\\/uploads\\/1483670370_focus_features_eternal_sunshine_of_the_spotless_mind_jim_carrey_kate_winslet_kirsten_dunst_mark_ruffalo_elijah_wood_michel_gondry_charlie_kaufman_gallery10.jpg\",\"video\":\"\"},{\"id\":\"photos_bts_3\",\"aid\":616,\"content_type\":\"image\",\"title\":\"\",\"short_desc\":\"\",\"description\":\"\",\"is_featured\":0,\"is_trailer\":0,\"external_url\":\"\",\"columns\":2,\"max_width\":1196,\"thumb\":\"http:\\/\\/focusmicrosites.s3.amazonaws.com\\/assets\\/uploads\\/_tmp\\/1483670402_focus_features_eternal_sunshine_of_the_spotless_mind_jim_carrey_kate_winslet_kirsten_dunst_mark_ruffalo_elijah_wood_michel_gondry_charlie_kaufman_gallery11-796x509.jpg\",\"related_items\":[],\"tags\":\" c125 c127 c129 c130 c135 c\",\"loop_vid\":0,\"img\":\"http:\\/\\/focusmicrosites.s3.amazonaws.com\\/assets\\/uploads\\/1483670402_focus_features_eternal_sunshine_of_the_spotless_mind_jim_carrey_kate_winslet_kirsten_dunst_mark_ruffalo_elijah_wood_michel_gondry_charlie_kaufman_gallery11.jpg\",\"video\":\"\"},{\"id\":\"photos_bts_4\",\"aid\":617,\"content_type\":\"image\",\"title\":\"\",\"short_desc\":\"\",\"description\":\"\",\"is_featured\":0,\"is_trailer\":0,\"external_url\":\"\",\"columns\":1,\"max_width\":1199,\"thumb\":\"http:\\/\\/focusmicrosites.s3.amazonaws.com\\/assets\\/uploads\\/_tmp\\/1483670425_focus_features_eternal_sunshine_of_the_spotless_mind_jim_carrey_kate_winslet_kirsten_dunst_mark_ruffalo_elijah_wood_michel_gondry_charlie_kaufman_gallery12-398x254.jpg\",\"related_items\":[],\"tags\":\" c125 c127 c129 c130 c135 c\",\"loop_vid\":0,\"img\":\"http:\\/\\/focusmicrosites.s3.amazonaws.com\\/assets\\/uploads\\/1483670425_focus_features_eternal_sunshine_of_the_spotless_mind_jim_carrey_kate_winslet_kirsten_dunst_mark_ruffalo_elijah_wood_michel_gondry_charlie_kaufman_gallery12.jpg\",\"video\":\"\"},{\"id\":\"photos_unit_1\",\"aid\":599,\"content_type\":\"image\",\"title\":\"\",\"short_desc\":\"\",\"description\":\"\",\"is_featured\":0,\"is_trailer\":0,\"external_url\":\"\",\"columns\":3,\"max_width\":1201,\"thumb\":\"http:\\/\\/focusmicrosites.s3.amazonaws.com\\/assets\\/uploads\\/_tmp\\/1483669879_focus_features_eternal_sunshine_of_the_spotless_mind_jim_carrey_kate_winslet_kirsten_dunst_mark_ruffalo_elijah_wood_michel_gondry_charlie_kaufman_gallery1-1194x778.jpg\",\"related_items\":[],\"tags\":\" c125 c126 c129 c130 c\",\"loop_vid\":0,\"img\":\"http:\\/\\/focusmicrosites.s3.amazonaws.com\\/assets\\/uploads\\/1483669879_focus_features_eternal_sunshine_of_the_spotless_mind_jim_carrey_kate_winslet_kirsten_dunst_mark_ruffalo_elijah_wood_michel_gondry_charlie_kaufman_gallery1.jpg\",\"video\":\"\"},{\"id\":\"photos_unit_12\",\"aid\":611,\"content_type\":\"image\",\"title\":\"\",\"short_desc\":\"\",\"description\":\"\",\"is_featured\":0,\"is_trailer\":0,\"external_url\":\"\",\"columns\":3,\"max_width\":2000,\"thumb\":\"http:\\/\\/focusmicrosites.s3.amazonaws.com\\/assets\\/uploads\\/_tmp\\/1483670255_focus_features_eternal_sunshine_of_the_spotless_mind_jim_carrey_kate_winslet_kirsten_dunst_mark_ruffalo_elijah_wood_michel_gondry_charlie_kaufman_gallery18-1194x595.jpg\",\"related_items\":[],\"tags\":\" c125 c126 c129 c130 c\",\"loop_vid\":0,\"img\":\"http:\\/\\/focusmicrosites.s3.amazonaws.com\\/assets\\/uploads\\/1483670255_focus_features_eternal_sunshine_of_the_spotless_mind_jim_carrey_kate_winslet_kirsten_dunst_mark_ruffalo_elijah_wood_michel_gondry_charlie_kaufman_gallery18.jpg\",\"video\":\"\"},{\"id\":\"photos_unit_2\",\"aid\":600,\"content_type\":\"image\",\"title\":\"\",\"short_desc\":\"\",\"description\":\"\",\"is_featured\":0,\"is_trailer\":0,\"external_url\":\"\",\"columns\":3,\"max_width\":1201,\"thumb\":\"http:\\/\\/focusmicrosites.s3.amazonaws.com\\/assets\\/uploads\\/_tmp\\/1483669915_focus_features_eternal_sunshine_of_the_spotless_mind_jim_carrey_kate_winslet_kirsten_dunst_mark_ruffalo_elijah_wood_michel_gondry_charlie_kaufman_gallery3-1194x640.jpg\",\"related_items\":[],\"tags\":\" c125 c126 c130 c\",\"loop_vid\":0,\"img\":\"http:\\/\\/focusmicrosites.s3.amazonaws.com\\/assets\\/uploads\\/1483669915_focus_features_eternal_sunshine_of_the_spotless_mind_jim_carrey_kate_winslet_kirsten_dunst_mark_ruffalo_elijah_wood_michel_gondry_charlie_kaufman_gallery3.jpg\",\"video\":\"\"},{\"id\":\"eternal_sunshine_of_the_spotless_mind_2005_academy_award_acceptance\",\"aid\":598,\"content_type\":\"video\",\"title\":\"<p>2005 Academy Awards: Best Original Screenplay<\\/p>\",\"short_desc\":\"<p>Charlie Kaufman accepts on behalf of Michele Gondry and Pierre Bismuth.<\\/p>\",\"description\":\"\",\"is_featured\":0,\"is_trailer\":0,\"external_url\":\"https:\\/\\/www.youtube.com\\/watch?v=a2Nav-ct3W8\",\"columns\":1,\"max_width\":0,\"thumb\":\"http:\\/\\/focusmicrosites.s3.amazonaws.com\\/assets\\/uploads\\/_tmp\\/1483668430_focus_features_eternal_sunshine_of_the_spotless_mind_jim_carrey_kate_winslet_kirsten_dunst_mark_ruffalo_elijah_wood_michel_gondry_charlie_kaufman_academyaward-398x262.jpg\",\"related_items\":[],\"tags\":\" c123 c124 c\",\"loop_vid\":0,\"img\":\"http:\\/\\/focusmicrosites.s3.amazonaws.com\\/assets\\/uploads\\/1483668430_focus_features_eternal_sunshine_of_the_spotless_mind_jim_carrey_kate_winslet_kirsten_dunst_mark_ruffalo_elijah_wood_michel_gondry_charlie_kaufman_academyaward.jpg\",\"video\":\"https:\\/\\/www.youtube.com\\/watch?v=a2Nav-ct3W8\"},{\"id\":\"594\",\"aid\":594,\"content_type\":\"quote\",\"title\":\"<p>NY Daily News - Jack Mathews - \\\"A masterpiece?\\\"<\\/p>\",\"short_desc\":\"\",\"description\":\"<p>A masterpiece? Probably. Ingenious? Absolutely! Unforgettable? I'll see you at the 10th-year anniversary.<\\/p>\",\"is_featured\":0,\"is_trailer\":0,\"external_url\":\"\",\"columns\":1,\"max_width\":0,\"thumb\":\"\",\"related_items\":[],\"tags\":\" c121 c122 c\",\"quote_author\":\"JACK MATHEWS\",\"quote_source\":\"THE NEW YORK DAILY NEWS\",\"rating\":\"\",\"rating_max\":4,\"loop_vid\":0,\"img\":\"\",\"video\":\"\"},{\"id\":\"597\",\"aid\":597,\"content_type\":\"quote\",\"title\":\"<p>Washington Post - Ann Hornaday - \\\"...the perfect movie...\\\"<\\/p>\",\"short_desc\":\"\",\"description\":\"<p>How sweetly ironic that <em>Eternal Sunshine of the Spotless Mind<\\/em> would turn out to be the perfect movie about love's inevitable imperfections.<\\/p>\",\"is_featured\":0,\"is_trailer\":0,\"external_url\":\"http:\\/\\/www.washingtonpost.com\\/wp-dyn\\/articles\\/A6624-2004Mar18.html\",\"columns\":1,\"max_width\":0,\"thumb\":\"\",\"related_items\":[],\"tags\":\" c121 c122 c\",\"quote_author\":\"ANN HORNADAY\",\"quote_source\":\"THE WASHINGTON POST\",\"rating\":\"\",\"rating_max\":4,\"loop_vid\":0,\"img\":\"\",\"video\":\"\"},{\"id\":\"photos_bts_5\",\"aid\":618,\"content_type\":\"image\",\"title\":\"\",\"short_desc\":\"\",\"description\":\"\",\"is_featured\":0,\"is_trailer\":0,\"external_url\":\"\",\"columns\":1,\"max_width\":1201,\"thumb\":\"http:\\/\\/focusmicrosites.s3.amazonaws.com\\/assets\\/uploads\\/_tmp\\/1483670457_focus_features_eternal_sunshine_of_the_spotless_mind_jim_carrey_kate_winslet_kirsten_dunst_mark_ruffalo_elijah_wood_michel_gondry_charlie_kaufman_gallery14-398x224.jpg\",\"related_items\":[],\"tags\":\" c125 c127 c130 c135 c136 c\",\"loop_vid\":0,\"img\":\"http:\\/\\/focusmicrosites.s3.amazonaws.com\\/assets\\/uploads\\/1483670457_focus_features_eternal_sunshine_of_the_spotless_mind_jim_carrey_kate_winslet_kirsten_dunst_mark_ruffalo_elijah_wood_michel_gondry_charlie_kaufman_gallery14.jpg\",\"video\":\"\"}],\"backgrounds\":[{\"id\":\"587\",\"aid\":587,\"content_type\":\"image\",\"loop_vid\":0,\"img\":\"http:\\/\\/focusmicrosites.s3.amazonaws.com\\/assets\\/uploads\\/1483665930_focus_features_eternal_sunshine_of_the_spotless_mind_jim_carrey_kate_winslet_kirsten_dunst_mark_ruffalo_elijah_wood_michel_gondry_charlie_kaufman_bg1a.jpg\",\"video\":\"\"},{\"id\":\"591\",\"aid\":591,\"content_type\":\"image\",\"loop_vid\":0,\"img\":\"http:\\/\\/focusmicrosites.s3.amazonaws.com\\/assets\\/uploads\\/1483666387_focus_features_eternal_sunshine_of_the_spotless_mind_jim_carrey_kate_winslet_kirsten_dunst_mark_ruffalo_elijah_wood_michel_gondry_charlie_kaufman_bg2.jpg\",\"video\":\"\"},{\"id\":\"590\",\"aid\":590,\"content_type\":\"image\",\"loop_vid\":0,\"img\":\"http:\\/\\/focusmicrosites.s3.amazonaws.com\\/assets\\/uploads\\/1483665963_focus_features_eternal_sunshine_of_the_spotless_mind_jim_carrey_kate_winslet_kirsten_dunst_mark_ruffalo_elijah_wood_michel_gondry_charlie_kaufman_bg4.jpg\",\"video\":\"\"},{\"id\":\"589\",\"aid\":589,\"content_type\":\"image\",\"loop_vid\":0,\"img\":\"http:\\/\\/focusmicrosites.s3.amazonaws.com\\/assets\\/uploads\\/1483665953_focus_features_eternal_sunshine_of_the_spotless_mind_jim_carrey_kate_winslet_kirsten_dunst_mark_ruffalo_elijah_wood_michel_gondry_charlie_kaufman_bg3.jpg\",\"video\":\"\"}],\"modules\":[{\"module_id\":\"3\",\"title\":\"OWN IT\",\"alignment\":\"left\"},{\"module_id\":\"6\",\"title\":\"REACTIONS\",\"alignment\":\"left\"},{\"module_id\":\"7\",\"title\":\"SOCIAL\",\"alignment\":\"right\"}],\"news\":[],\"partners\":[],\"reactions\":[{\"title\":\"\",\"source\":\"\",\"author\":\"\",\"url\":\"https:\\/\\/www.rottentomatoes.com\\/m\\/eternal_sunshine_of_the_spotless_mind\\/\",\"img\":\"http:\\/\\/focusmicrosites.s3.amazonaws.com\\/assets\\/uploads\\/reactions_1483741687.jpg\"},{\"title\":\"89\",\"source\":\"METACRITIC\",\"author\":\"\",\"url\":\"http:\\/\\/www.metacritic.com\\/movie\\/eternal-sunshine-of-the-spotless-mind\\/critic-reviews\",\"img\":\"\"},{\"title\":\"8.3\",\"source\":\"IMDB\",\"author\":\"\",\"url\":\"http:\\/\\/www.imdb.com\\/title\\/tt0338013\\/?ref_=ttqt_qt_tt\",\"img\":\"\"}],\"trending\":[],\"castcrew\":[{\"id\":\"3326\",\"full_name\":\"Jim Carrey\",\"person_role\":\"<p>Joel Barish<\\/p>\",\"url\":\"\",\"is_cast\":\"1\"},{\"id\":\"3328\",\"full_name\":\"Kate Winslet\",\"person_role\":\"<p>Clementine Kruczynski<\\/p>\",\"url\":\"\",\"is_cast\":\"1\"},{\"id\":\"3330\",\"full_name\":\"Kirsten Dunst\",\"person_role\":\"<p>Mary<\\/p>\",\"url\":\"\",\"is_cast\":\"1\"},{\"id\":\"3332\",\"full_name\":\"Mark Ruffalo\",\"person_role\":\"<p>Stan<\\/p>\",\"url\":\"\",\"is_cast\":\"1\"},{\"id\":\"3334\",\"full_name\":\"Elijah Wood\",\"person_role\":\"<p>Patrick<\\/p>\",\"url\":\"\",\"is_cast\":\"1\"},{\"id\":\"3336\",\"full_name\":\"Tom Wilkinson\",\"person_role\":\"<p>Dr. Howard Mierzwiak<\\/p>\",\"url\":\"\",\"is_cast\":\"1\"},{\"id\":\"3325\",\"full_name\":\"Michel Gondry\",\"person_role\":\"<p>Director<\\/p>\",\"url\":\"\",\"is_cast\":\"0\"},{\"id\":\"3327\",\"full_name\":\"Charlie Kaufman\",\"person_role\":\"<p>Writer<\\/p>\",\"url\":\"\",\"is_cast\":\"0\"},{\"id\":\"3329\",\"full_name\":\"Pierre Bismuth\",\"person_role\":\"<p>Writer<\\/p>\",\"url\":\"\",\"is_cast\":\"0\"},{\"id\":\"3331\",\"full_name\":\"Steve Golin\",\"person_role\":\"<p>Producer<\\/p>\",\"url\":\"\",\"is_cast\":\"0\"},{\"id\":\"3333\",\"full_name\":\"Anthony Bregman\",\"person_role\":\"<p>Producer<\\/p>\",\"url\":\"\",\"is_cast\":\"0\"},{\"id\":\"3335\",\"full_name\":\"David Bushell\",\"person_role\":\"<p>Executive Producer<\\/p>\",\"url\":\"\",\"is_cast\":\"0\"},{\"id\":\"3337\",\"full_name\":\"Glenn Williamson\",\"person_role\":\"<p>Executive Producer<\\/p>\",\"url\":\"\",\"is_cast\":\"0\"},{\"id\":\"3338\",\"full_name\":\"Georges Bermann\",\"person_role\":\"<p>Executive Producer<\\/p>\",\"url\":\"\",\"is_cast\":\"0\"},{\"id\":\"3339\",\"full_name\":\"Ellen Kuras\",\"person_role\":\"<p>Director of Photography<\\/p>\",\"url\":\"\",\"is_cast\":\"0\"},{\"id\":\"3340\",\"full_name\":\"Dan Leigh\",\"person_role\":\"<p>Production Designer<\\/p>\",\"url\":\"\",\"is_cast\":\"0\"},{\"id\":\"3341\",\"full_name\":\"Valdis Oskarsdottir\",\"person_role\":\"<p>Editor<\\/p>\",\"url\":\"\",\"is_cast\":\"0\"},{\"id\":\"3342\",\"full_name\":\"Jon Brion\",\"person_role\":\"<p>Composer<\\/p>\",\"url\":\"\",\"is_cast\":\"0\"},{\"id\":\"3343\",\"full_name\":\"Melissa Toth\",\"person_role\":\"<p>Costume Designer<\\/p>\",\"url\":\"\",\"is_cast\":\"0\"}],\"awards\":[{\"category_head\":\"Academy Awards\",\"category\":\"Academy Awards\",\"award_category\":\"Original Screenplay\",\"people\":\"Charlie Kaufman, Michel Gondry, Pierre Bismuth\",\"is_winner\":1}]},\"spriteVersion\":\"13\",\"cssVersion\":\"118.13\",\"jsVersion\":\"117.13\",\"jsonPath\":\"http:\\/\\/focusmicrosites.s3.amazonaws.com\\/assets\\/uploads\\/_tmp\\/productionseternal_sunshine_of_the_spotless_mind\",\"status\":\"ok\",\"usedDB\":0}}"], "url": "focusfeatures.com/eternal_sunshine_of_the_spotless_mind", "_type": "x"}